BeginnersbookKotlinJiaochengChuyiFix1/README.md
BeginnersbookKotlinJiaochengChuyiFix1/__init__.py
BeginnersbookKotlinJiaochengChuyiFix1/__main__.py
BeginnersbookKotlinJiaochengChuyiFix1/file.epub
BeginnersbookKotlinJiaochengChuyiFix1/index.html
BeginnersbookKotlinJiaochengChuyiFix1/css/__init__.py
BeginnersbookKotlinJiaochengChuyiFix1/css/annotations.css
BeginnersbookKotlinJiaochengChuyiFix1/css/main.css
BeginnersbookKotlinJiaochengChuyiFix1/css/normalize.css
BeginnersbookKotlinJiaochengChuyiFix1/css/popup.css
BeginnersbookKotlinJiaochengChuyiFix1/font/__init__.py
BeginnersbookKotlinJiaochengChuyiFix1/font/fontello.eot
BeginnersbookKotlinJiaochengChuyiFix1/font/fontello.svg
BeginnersbookKotlinJiaochengChuyiFix1/font/fontello.ttf
BeginnersbookKotlinJiaochengChuyiFix1/font/fontello.woff
BeginnersbookKotlinJiaochengChuyiFix1/img/__init__.py
BeginnersbookKotlinJiaochengChuyiFix1/img/annotator-glyph-sprite.png
BeginnersbookKotlinJiaochengChuyiFix1/img/annotator-icon-sprite.png
BeginnersbookKotlinJiaochengChuyiFix1/img/apple-touch-icon.png
BeginnersbookKotlinJiaochengChuyiFix1/img/cancelfullscreen.png
BeginnersbookKotlinJiaochengChuyiFix1/img/close.png
BeginnersbookKotlinJiaochengChuyiFix1/img/fullscreen.png
BeginnersbookKotlinJiaochengChuyiFix1/img/loader.gif
BeginnersbookKotlinJiaochengChuyiFix1/img/menu-icon.png
BeginnersbookKotlinJiaochengChuyiFix1/img/save.png
BeginnersbookKotlinJiaochengChuyiFix1/img/saved.png
BeginnersbookKotlinJiaochengChuyiFix1/img/settings-s.png
BeginnersbookKotlinJiaochengChuyiFix1/img/settings.png
BeginnersbookKotlinJiaochengChuyiFix1/img/star.png
BeginnersbookKotlinJiaochengChuyiFix1/js/__init__.py
BeginnersbookKotlinJiaochengChuyiFix1/js/epub.js
BeginnersbookKotlinJiaochengChuyiFix1/js/epub.min.js
BeginnersbookKotlinJiaochengChuyiFix1/js/epub.min.map
BeginnersbookKotlinJiaochengChuyiFix1/js/hooks.min.js
BeginnersbookKotlinJiaochengChuyiFix1/js/hooks.min.map
BeginnersbookKotlinJiaochengChuyiFix1/js/reader.js
beginnersbook_kotlin_jiaocheng_chuyi_fix1-2025.3.24.0.dist-info/METADATA
beginnersbook_kotlin_jiaocheng_chuyi_fix1-2025.3.24.0.dist-info/WHEEL
beginnersbook_kotlin_jiaocheng_chuyi_fix1-2025.3.24.0.dist-info/entry_points.txt
beginnersbook_kotlin_jiaocheng_chuyi_fix1-2025.3.24.0.dist-info/top_level.txt
beginnersbook_kotlin_jiaocheng_chuyi_fix1-2025.3.24.0.dist-info/RECORD
